--- Compact Bytecode of test_pipeline ---
L12:    0: RESUME               (0)
L13:    2: LOAD_GLOBAL          (os)
     14: LOAD_ATTR            (path)
     24: LOAD_METHOD          (exists)
     46: LOAD_CONST           (checkpoints)
     48: PRECALL              (1)
     52: CALL                 (1)
     62: POP_JUMP_FORWARD_IF_FALSE (104)
L14:   64: LOAD_GLOBAL          (shutil)
     76: LOAD_ATTR            (rmtree)
     86: LOAD_CONST           (checkpoints)
     88: PRECALL              (1)
     92: CALL                 (1)
    102: POP_TOP             
L16:  104: LOAD_GLOBAL          (S1IdeationAgent)
    116: PRECALL              (0)
    120: CALL                 (0)
    130: STORE_FAST           (s1)
L17:  132: LOAD_FAST            (s1)
    134: LOAD_METHOD          (run)
    156: LOAD_CONST           (input)
    158: LOAD_CONST           (Build a habit tracker app for iOS with React and Python. It should track daily habits, and should show progress charts.)
    160: BUILD_MAP            (1)
    162: PRECALL              (1)
    166: CALL                 (1)
    176: STORE_FAST           (concept)
L18:  178: LOAD_FAST            (concept)
    180: LOAD_CONST           (status)
    182: BINARY_SUBSCR       
    192: STORE_FAST           (@py_assert0)
    194: LOAD_CONST           (complete)
    196: STORE_FAST           (@py_assert3)
    198: LOAD_FAST            (@py_assert0)
    200: LOAD_FAST            (@py_assert3)
    202: COMPARE_OP           (==)
    208: STORE_FAST           (@py_assert2)
    210: LOAD_FAST            (@py_assert2)
    212: POP_JUMP_FORWARD_IF_TRUE (430)
    214: LOAD_GLOBAL          (@pytest_ar)
    226: LOAD_ATTR            (_call_reprcompare)
    236: LOAD_CONST           (('==',))
    238: LOAD_FAST            (@py_assert2)
    240: BUILD_TUPLE          (1)
    242: LOAD_CONST           (('%(py1)s == %(py4)s',))
    244: LOAD_FAST            (@py_assert0)
    246: LOAD_FAST            (@py_assert3)
    248: BUILD_TUPLE          (2)
    250: PRECALL              (4)
    254: CALL                 (4)
    264: LOAD_GLOBAL          (@pytest_ar)
    276: LOAD_ATTR            (_saferepr)
    286: LOAD_FAST            (@py_assert0)
    288: PRECALL              (1)
    292: CALL                 (1)
    302: LOAD_GLOBAL          (@pytest_ar)
    314: LOAD_ATTR            (_saferepr)
    324: LOAD_FAST            (@py_assert3)
    326: PRECALL              (1)
    330: CALL                 (1)
    340: LOAD_CONST           (('py1', 'py4'))
    342: BUILD_CONST_KEY_MAP  (2)
    344: BINARY_OP            (6)
    348: STORE_FAST           (@py_format5)
    350: LOAD_CONST           (assert %(py6)s)
    352: LOAD_CONST           (py6)
    354: LOAD_FAST            (@py_format5)
    356: BUILD_MAP            (1)
    358: BINARY_OP            (6)
    362: STORE_FAST           (@py_format7)
    364: LOAD_GLOBAL          (AssertionError)
    376: LOAD_GLOBAL          (@pytest_ar)
    388: LOAD_ATTR            (_format_explanation)
    398: LOAD_FAST            (@py_format7)
    400: PRECALL              (1)
    404: CALL                 (1)
    414: PRECALL              (1)
    418: CALL                 (1)
    428: RAISE_VARARGS        (1)
    430: LOAD_CONST           (None)
    432: COPY                 (1)
    434: STORE_FAST           (@py_assert0)
    436: COPY                 (1)
    438: STORE_FAST           (@py_assert2)
    440: STORE_FAST           (@py_assert3)
L19:  442: LOAD_CONST           (habit tracker)
    444: STORE_FAST           (@py_assert0)
    446: LOAD_FAST            (concept)
    448: LOAD_CONST           (concept)
    450: BINARY_SUBSCR       
    460: LOAD_CONST           (title)
    462: BINARY_SUBSCR       
    472: STORE_FAST           (@py_assert3)
    474: LOAD_FAST            (@py_assert3)
    476: LOAD_ATTR            (lower)
    486: STORE_FAST           (@py_assert5)
    488: PUSH_NULL           
    490: LOAD_FAST            (@py_assert5)
    492: PRECALL              (0)
    496: CALL                 (0)
    506: STORE_FAST           (@py_assert7)
    508: LOAD_FAST            (@py_assert0)
    510: LOAD_FAST            (@py_assert7)
    512: CONTAINS_OP          (0)
    514: STORE_FAST           (@py_assert2)
    516: LOAD_FAST            (@py_assert2)
    518: POP_JUMP_FORWARD_IF_TRUE (812)
    520: LOAD_GLOBAL          (@pytest_ar)
    532: LOAD_ATTR            (_call_reprcompare)
    542: LOAD_CONST           (('in',))
    544: LOAD_FAST            (@py_assert2)
    546: BUILD_TUPLE          (1)
    548: LOAD_CONST           (('%(py1)s in %(py8)s\n{%(py8)s = %(py6)s\n{%(py6)s = %(py4)s.lower\n}()\n}',))
    550: LOAD_FAST            (@py_assert0)
    552: LOAD_FAST            (@py_assert7)
    554: BUILD_TUPLE          (2)
    556: PRECALL              (4)
    560: CALL                 (4)
    570: LOAD_GLOBAL          (@pytest_ar)
    582: LOAD_ATTR            (_saferepr)
    592: LOAD_FAST            (@py_assert0)
    594: PRECALL              (1)
    598: CALL                 (1)
    608: LOAD_GLOBAL          (@pytest_ar)
    620: LOAD_ATTR            (_saferepr)
    630: LOAD_FAST            (@py_assert3)
    632: PRECALL              (1)
    636: CALL                 (1)
    646: LOAD_GLOBAL          (@pytest_ar)
    658: LOAD_ATTR            (_saferepr)
    668: LOAD_FAST            (@py_assert5)
    670: PRECALL              (1)
    674: CALL                 (1)
    684: LOAD_GLOBAL          (@pytest_ar)
    696: LOAD_ATTR            (_saferepr)
    706: LOAD_FAST            (@py_assert7)
    708: PRECALL              (1)
    712: CALL                 (1)
    722: LOAD_CONST           (('py1', 'py4', 'py6', 'py8'))
    724: BUILD_CONST_KEY_MAP  (4)
    726: BINARY_OP            (6)
    730: STORE_FAST           (@py_format9)
    732: LOAD_CONST           (assert %(py10)s)
    734: LOAD_CONST           (py10)
    736: LOAD_FAST            (@py_format9)
    738: BUILD_MAP            (1)
    740: BINARY_OP            (6)
    744: STORE_FAST           (@py_format11)
    746: LOAD_GLOBAL          (AssertionError)
    758: LOAD_GLOBAL          (@pytest_ar)
    770: LOAD_ATTR            (_format_explanation)
    780: LOAD_FAST            (@py_format11)
    782: PRECALL              (1)
    786: CALL                 (1)
    796: PRECALL              (1)
    800: CALL                 (1)
    810: RAISE_VARARGS        (1)
    812: LOAD_CONST           (None)
    814: COPY                 (1)
    816: STORE_FAST           (@py_assert0)
    818: COPY                 (1)
    820: STORE_FAST           (@py_assert2)
    822: COPY                 (1)
    824: STORE_FAST           (@py_assert3)
    826: COPY                 (1)
    828: STORE_FAST           (@py_assert5)
    830: STORE_FAST           (@py_assert7)
L20:  832: LOAD_CONST           (react)
    834: STORE_FAST           (@py_assert0)
    836: LOAD_FAST            (concept)
    838: LOAD_CONST           (concept)
    840: BINARY_SUBSCR       
    850: LOAD_CONST           (tech_stack_hints)
    852: BINARY_SUBSCR       
    862: STORE_FAST           (@py_assert3)
    864: LOAD_FAST            (@py_assert0)
    866: LOAD_FAST            (@py_assert3)
    868: CONTAINS_OP          (0)
    870: STORE_FAST           (@py_assert2)
    872: LOAD_FAST            (@py_assert2)
    874: POP_JUMP_FORWARD_IF_TRUE (1092)
    876: LOAD_GLOBAL          (@pytest_ar)
    888: LOAD_ATTR            (_call_reprcompare)
    898: LOAD_CONST           (('in',))
    900: LOAD_FAST            (@py_assert2)
    902: BUILD_TUPLE          (1)
    904: LOAD_CONST           (('%(py1)s in %(py4)s',))
    906: LOAD_FAST            (@py_assert0)
    908: LOAD_FAST            (@py_assert3)
    910: BUILD_TUPLE          (2)
    912: PRECALL              (4)
    916: CALL                 (4)
    926: LOAD_GLOBAL          (@pytest_ar)
    938: LOAD_ATTR            (_saferepr)
    948: LOAD_FAST            (@py_assert0)
    950: PRECALL              (1)
    954: CALL                 (1)
    964: LOAD_GLOBAL          (@pytest_ar)
    976: LOAD_ATTR            (_saferepr)
    986: LOAD_FAST            (@py_assert3)
    988: PRECALL              (1)
    992: CALL                 (1)
   1002: LOAD_CONST           (('py1', 'py4'))
   1004: BUILD_CONST_KEY_MAP  (2)
   1006: BINARY_OP            (6)
   1010: STORE_FAST           (@py_format5)
   1012: LOAD_CONST           (assert %(py6)s)
   1014: LOAD_CONST           (py6)
   1016: LOAD_FAST            (@py_format5)
   1018: BUILD_MAP            (1)
   1020: BINARY_OP            (6)
   1024: STORE_FAST           (@py_format7)
   1026: LOAD_GLOBAL          (AssertionError)
   1038: LOAD_GLOBAL          (@pytest_ar)
   1050: LOAD_ATTR            (_format_explanation)
   1060: LOAD_FAST            (@py_format7)
   1062: PRECALL              (1)
   1066: CALL                 (1)
   1076: PRECALL              (1)
   1080: CALL                 (1)
   1090: RAISE_VARARGS        (1)
   1092: LOAD_CONST           (None)
   1094: COPY                 (1)
   1096: STORE_FAST           (@py_assert0)
   1098: COPY                 (1)
   1100: STORE_FAST           (@py_assert2)
   1102: STORE_FAST           (@py_assert3)
L21: 1104: LOAD_CONST           (python)
   1106: STORE_FAST           (@py_assert0)
   1108: LOAD_FAST            (concept)
   1110: LOAD_CONST           (concept)
   1112: BINARY_SUBSCR       
   1122: LOAD_CONST           (tech_stack_hints)
   1124: BINARY_SUBSCR       
   1134: STORE_FAST           (@py_assert3)
   1136: LOAD_FAST            (@py_assert0)
   1138: LOAD_FAST            (@py_assert3)
   1140: CONTAINS_OP          (0)
   1142: STORE_FAST           (@py_assert2)
   1144: LOAD_FAST            (@py_assert2)
   1146: POP_JUMP_FORWARD_IF_TRUE (1364)
   1148: LOAD_GLOBAL          (@pytest_ar)
   1160: LOAD_ATTR            (_call_reprcompare)
   1170: LOAD_CONST           (('in',))
   1172: LOAD_FAST            (@py_assert2)
   1174: BUILD_TUPLE          (1)
   1176: LOAD_CONST           (('%(py1)s in %(py4)s',))
   1178: LOAD_FAST            (@py_assert0)
   1180: LOAD_FAST            (@py_assert3)
   1182: BUILD_TUPLE          (2)
   1184: PRECALL              (4)
   1188: CALL                 (4)
   1198: LOAD_GLOBAL          (@pytest_ar)
   1210: LOAD_ATTR            (_saferepr)
   1220: LOAD_FAST            (@py_assert0)
   1222: PRECALL              (1)
   1226: CALL                 (1)
   1236: LOAD_GLOBAL          (@pytest_ar)
   1248: LOAD_ATTR            (_saferepr)
   1258: LOAD_FAST            (@py_assert3)
   1260: PRECALL              (1)
   1264: CALL                 (1)
   1274: LOAD_CONST           (('py1', 'py4'))
   1276: BUILD_CONST_KEY_MAP  (2)
   1278: BINARY_OP            (6)
   1282: STORE_FAST           (@py_format5)
   1284: LOAD_CONST           (assert %(py6)s)
   1286: LOAD_CONST           (py6)
   1288: LOAD_FAST            (@py_format5)
   1290: BUILD_MAP            (1)
   1292: BINARY_OP            (6)
   1296: STORE_FAST           (@py_format7)
   1298: LOAD_GLOBAL          (AssertionError)
   1310: LOAD_GLOBAL          (@pytest_ar)
   1322: LOAD_ATTR            (_format_explanation)
   1332: LOAD_FAST            (@py_format7)
   1334: PRECALL              (1)
   1338: CALL                 (1)
   1348: PRECALL              (1)
   1352: CALL                 (1)
   1362: RAISE_VARARGS        (1)
   1364: LOAD_CONST           (None)
   1366: COPY                 (1)
   1368: STORE_FAST           (@py_assert0)
   1370: COPY                 (1)
   1372: STORE_FAST           (@py_assert2)
   1374: STORE_FAST           (@py_assert3)
L22: 1376: LOAD_GLOBAL          (print)
   1388: LOAD_CONST           (S1 PASS: )
   1390: LOAD_FAST            (concept)
   1392: LOAD_CONST           (concept)
   1394: BINARY_SUBSCR       
   1404: LOAD_CONST           (title)
   1406: BINARY_SUBSCR       
   1416: FORMAT_VALUE         ((None, False))
   1418: BUILD_STRING         (2)
   1420: PRECALL              (1)
   1424: CALL                 (1)
   1434: POP_TOP             
L25: 1436: LOAD_GLOBAL          (S2ResearchAgent)
   1448: PRECALL              (0)
   1452: CALL                 (0)
   1462: STORE_FAST           (s2)
L26: 1464: LOAD_FAST            (s2)
   1466: LOAD_METHOD          (run)
   1488: LOAD_CONST           (concept)
   1490: LOAD_FAST            (concept)
   1492: LOAD_CONST           (concept)
   1494: BINARY_SUBSCR       
   1504: BUILD_MAP            (1)
   1506: PRECALL              (1)
   1510: CALL                 (1)
   1520: STORE_FAST           (research)
L27: 1522: LOAD_FAST            (research)
   1524: LOAD_CONST           (status)
   1526: BINARY_SUBSCR       
   1536: STORE_FAST           (@py_assert0)
   1538: LOAD_CONST           (complete)
   1540: STORE_FAST           (@py_assert3)
   1542: LOAD_FAST            (@py_assert0)
   1544: LOAD_FAST            (@py_assert3)
   1546: COMPARE_OP           (==)
   1552: STORE_FAST           (@py_assert2)
   1554: LOAD_FAST            (@py_assert2)
   1556: POP_JUMP_FORWARD_IF_TRUE (1774)
   1558: LOAD_GLOBAL          (@pytest_ar)
   1570: LOAD_ATTR            (_call_reprcompare)
   1580: LOAD_CONST           (('==',))
   1582: LOAD_FAST            (@py_assert2)
   1584: BUILD_TUPLE          (1)
   1586: LOAD_CONST           (('%(py1)s == %(py4)s',))
   1588: LOAD_FAST            (@py_assert0)
   1590: LOAD_FAST            (@py_assert3)
   1592: BUILD_TUPLE          (2)
   1594: PRECALL              (4)
   1598: CALL                 (4)
   1608: LOAD_GLOBAL          (@pytest_ar)
   1620: LOAD_ATTR            (_saferepr)
   1630: LOAD_FAST            (@py_assert0)
   1632: PRECALL              (1)
   1636: CALL                 (1)
   1646: LOAD_GLOBAL          (@pytest_ar)
   1658: LOAD_ATTR            (_saferepr)
   1668: LOAD_FAST            (@py_assert3)
   1670: PRECALL              (1)
   1674: CALL                 (1)
   1684: LOAD_CONST           (('py1', 'py4'))
   1686: BUILD_CONST_KEY_MAP  (2)
   1688: BINARY_OP            (6)
   1692: STORE_FAST           (@py_format5)
   1694: LOAD_CONST           (assert %(py6)s)
   1696: LOAD_CONST           (py6)
   1698: LOAD_FAST            (@py_format5)
   1700: BUILD_MAP            (1)
   1702: BINARY_OP            (6)
   1706: STORE_FAST           (@py_format7)
   1708: LOAD_GLOBAL          (AssertionError)
   1720: LOAD_GLOBAL          (@pytest_ar)
   1732: LOAD_ATTR            (_format_explanation)
   1742: LOAD_FAST            (@py_format7)
   1744: PRECALL              (1)
   1748: CALL                 (1)
   1758: PRECALL              (1)
   1762: CALL                 (1)
   1772: RAISE_VARARGS        (1)
   1774: LOAD_CONST           (None)
   1776: COPY                 (1)
   1778: STORE_FAST           (@py_assert0)
   1780: COPY                 (1)
   1782: STORE_FAST           (@py_assert2)
   1784: STORE_FAST           (@py_assert3)
L28: 1786: LOAD_FAST            (research)
   1788: LOAD_CONST           (sources)
   1790: BINARY_SUBSCR       
   1800: STORE_FAST           (@py_assert1)
   1802: LOAD_GLOBAL          (len)
   1814: LOAD_FAST            (@py_assert1)
   1816: PRECALL              (1)
   1820: CALL                 (1)
   1830: STORE_FAST           (@py_assert3)
   1832: LOAD_CONST           (0)
   1834: STORE_FAST           (@py_assert6)
   1836: LOAD_FAST            (@py_assert3)
   1838: LOAD_FAST            (@py_assert6)
   1840: COMPARE_OP           (>)
   1846: STORE_FAST           (@py_assert5)
   1848: LOAD_FAST            (@py_assert5)
   1850: POP_JUMP_FORWARD_IF_TRUE (2250)
   1852: LOAD_GLOBAL          (@pytest_ar)
   1864: LOAD_ATTR            (_call_reprcompare)
   1874: LOAD_CONST           (('>',))
   1876: LOAD_FAST            (@py_assert5)
   1878: BUILD_TUPLE          (1)
   1880: LOAD_CONST           (('%(py4)s\n{%(py4)s = %(py0)s(%(py2)s)\n} > %(py7)s',))
   1882: LOAD_FAST            (@py_assert3)
   1884: LOAD_FAST            (@py_assert6)
   1886: BUILD_TUPLE          (2)
   1888: PRECALL              (4)
   1892: CALL                 (4)
   1902: LOAD_CONST           (len)
   1904: LOAD_GLOBAL          (@py_builtins)
   1916: LOAD_ATTR            (locals)
   1926: PRECALL              (0)
   1930: CALL                 (0)
   1940: CONTAINS_OP          (0)
   1942: POP_JUMP_FORWARD_IF_TRUE (1994)
   1944: LOAD_GLOBAL          (@pytest_ar)
   1956: LOAD_ATTR            (_should_repr_global_name)
   1966: LOAD_GLOBAL          (len)
   1978: PRECALL              (1)
   1982: CALL                 (1)
   1992: POP_JUMP_FORWARD_IF_FALSE (2044)
   1994: LOAD_GLOBAL          (@pytest_ar)
   2006: LOAD_ATTR            (_saferepr)
   2016: LOAD_GLOBAL          (len)
   2028: PRECALL              (1)
   2032: CALL                 (1)
   2042: JUMP_FORWARD         (2046)
   2044: LOAD_CONST           (len)
   2046: LOAD_GLOBAL          (@pytest_ar)
   2058: LOAD_ATTR            (_saferepr)
   2068: LOAD_FAST            (@py_assert1)
   2070: PRECALL              (1)
   2074: CALL                 (1)
   2084: LOAD_GLOBAL          (@pytest_ar)
   2096: LOAD_ATTR            (_saferepr)
   2106: LOAD_FAST            (@py_assert3)
   2108: PRECALL              (1)
   2112: CALL                 (1)
   2122: LOAD_GLOBAL          (@pytest_ar)
   2134: LOAD_ATTR            (_saferepr)
   2144: LOAD_FAST            (@py_assert6)
   2146: PRECALL              (1)
   2150: CALL                 (1)
   2160: LOAD_CONST           (('py0', 'py2', 'py4', 'py7'))
   2162: BUILD_CONST_KEY_MAP  (4)
   2164: BINARY_OP            (6)
   2168: STORE_FAST           (@py_format8)
   2170: LOAD_CONST           (assert %(py9)s)
   2172: LOAD_CONST           (py9)
   2174: LOAD_FAST            (@py_format8)
   2176: BUILD_MAP            (1)
   2178: BINARY_OP            (6)
   2182: STORE_FAST           (@py_format10)
   2184: LOAD_GLOBAL          (AssertionError)
   2196: LOAD_GLOBAL          (@pytest_ar)
   2208: LOAD_ATTR            (_format_explanation)
   2218: LOAD_FAST            (@py_format10)
   2220: PRECALL              (1)
   2224: CALL                 (1)
   2234: PRECALL              (1)
   2238: CALL                 (1)
   2248: RAISE_VARARGS        (1)
   2250: LOAD_CONST           (None)
   2252: COPY                 (1)
   2254: STORE_FAST           (@py_assert1)
   2256: COPY                 (1)
   2258: STORE_FAST           (@py_assert3)
   2260: COPY                 (1)
   2262: STORE_FAST           (@py_assert5)
   2264: STORE_FAST           (@py_assert6)
L29: 2266: LOAD_GLOBAL          (print)
   2278: LOAD_CONST           (S2 PASS: )
   2280: LOAD_GLOBAL          (len)
   2292: LOAD_FAST            (research)
   2294: LOAD_CONST           (sources)
   2296: BINARY_SUBSCR       
   2306: PRECALL              (1)
   2310: CALL                 (1)
   2320: FORMAT_VALUE         ((None, False))
   2322: LOAD_CONST           ( sources found)
   2324: BUILD_STRING         (3)
   2326: PRECALL              (1)
   2330: CALL                 (1)
   2340: POP_TOP             
L32: 2342: LOAD_GLOBAL          (S3PRDAgent)
   2354: PRECALL              (0)
   2358: CALL                 (0)
   2368: STORE_FAST           (s3)
L33: 2370: LOAD_FAST            (s3)
   2372: LOAD_METHOD          (run)
   2394: LOAD_FAST            (concept)
   2396: LOAD_CONST           (concept)
   2398: BINARY_SUBSCR       
   2408: LOAD_FAST            (research)
   2410: LOAD_CONST           (research_summary)
   2412: BINARY_SUBSCR       
   2422: LOAD_CONST           (('concept', 'research_summary'))
   2424: BUILD_CONST_KEY_MAP  (2)
   2426: PRECALL              (1)
   2430: CALL                 (1)
   2440: STORE_FAST           (prd)
L34: 2442: LOAD_FAST            (prd)
   2444: LOAD_CONST           (status)
   2446: BINARY_SUBSCR       
   2456: STORE_FAST           (@py_assert0)
   2458: LOAD_CONST           (complete)
   2460: STORE_FAST           (@py_assert3)
   2462: LOAD_FAST            (@py_assert0)
   2464: LOAD_FAST            (@py_assert3)
   2466: COMPARE_OP           (==)
   2472: STORE_FAST           (@py_assert2)
   2474: LOAD_FAST            (@py_assert2)
   2476: POP_JUMP_FORWARD_IF_TRUE (2694)
   2478: LOAD_GLOBAL          (@pytest_ar)
   2490: LOAD_ATTR            (_call_reprcompare)
   2500: LOAD_CONST           (('==',))
   2502: LOAD_FAST            (@py_assert2)
   2504: BUILD_TUPLE          (1)
   2506: LOAD_CONST           (('%(py1)s == %(py4)s',))
   2508: LOAD_FAST            (@py_assert0)
   2510: LOAD_FAST            (@py_assert3)
   2512: BUILD_TUPLE          (2)
   2514: PRECALL              (4)
   2518: CALL                 (4)
   2528: LOAD_GLOBAL          (@pytest_ar)
   2540: LOAD_ATTR            (_saferepr)
   2550: LOAD_FAST            (@py_assert0)
   2552: PRECALL              (1)
   2556: CALL                 (1)
   2566: LOAD_GLOBAL          (@pytest_ar)
   2578: LOAD_ATTR            (_saferepr)
   2588: LOAD_FAST            (@py_assert3)
   2590: PRECALL              (1)
   2594: CALL                 (1)
   2604: LOAD_CONST           (('py1', 'py4'))
   2606: BUILD_CONST_KEY_MAP  (2)
   2608: BINARY_OP            (6)
   2612: STORE_FAST           (@py_format5)
   2614: LOAD_CONST           (assert %(py6)s)
   2616: LOAD_CONST           (py6)
   2618: LOAD_FAST            (@py_format5)
   2620: BUILD_MAP            (1)
   2622: BINARY_OP            (6)
   2626: STORE_FAST           (@py_format7)
   2628: LOAD_GLOBAL          (AssertionError)
   2640: LOAD_GLOBAL          (@pytest_ar)
   2652: LOAD_ATTR            (_format_explanation)
   2662: LOAD_FAST            (@py_format7)
   2664: PRECALL              (1)
   2668: CALL                 (1)
   2678: PRECALL              (1)
   2682: CALL                 (1)
   2692: RAISE_VARARGS        (1)
   2694: LOAD_CONST           (None)
   2696: COPY                 (1)
   2698: STORE_FAST           (@py_assert0)
   2700: COPY                 (1)
   2702: STORE_FAST           (@py_assert2)
   2704: STORE_FAST           (@py_assert3)
L35: 2706: LOAD_CONST           (metadata)
   2708: STORE_FAST           (@py_assert0)
   2710: LOAD_FAST            (prd)
   2712: LOAD_CONST           (prd)
   2714: BINARY_SUBSCR       
   2724: STORE_FAST           (@py_assert3)
   2726: LOAD_FAST            (@py_assert0)
   2728: LOAD_FAST            (@py_assert3)
   2730: CONTAINS_OP          (0)
   2732: STORE_FAST           (@py_assert2)
   2734: LOAD_FAST            (@py_assert2)
   2736: POP_JUMP_FORWARD_IF_TRUE (2954)
   2738: LOAD_GLOBAL          (@pytest_ar)
   2750: LOAD_ATTR            (_call_reprcompare)
   2760: LOAD_CONST           (('in',))
   2762: LOAD_FAST            (@py_assert2)
   2764: BUILD_TUPLE          (1)
   2766: LOAD_CONST           (('%(py1)s in %(py4)s',))
   2768: LOAD_FAST            (@py_assert0)
   2770: LOAD_FAST            (@py_assert3)
   2772: BUILD_TUPLE          (2)
   2774: PRECALL              (4)
   2778: CALL                 (4)
   2788: LOAD_GLOBAL          (@pytest_ar)
   2800: LOAD_ATTR            (_saferepr)
   2810: LOAD_FAST            (@py_assert0)
   2812: PRECALL              (1)
   2816: CALL                 (1)
   2826: LOAD_GLOBAL          (@pytest_ar)
   2838: LOAD_ATTR            (_saferepr)
   2848: LOAD_FAST            (@py_assert3)
   2850: PRECALL              (1)
   2854: CALL                 (1)
   2864: LOAD_CONST           (('py1', 'py4'))
   2866: BUILD_CONST_KEY_MAP  (2)
   2868: BINARY_OP            (6)
   2872: STORE_FAST           (@py_format5)
   2874: LOAD_CONST           (assert %(py6)s)
   2876: LOAD_CONST           (py6)
   2878: LOAD_FAST            (@py_format5)
   2880: BUILD_MAP            (1)
   2882: BINARY_OP            (6)
   2886: STORE_FAST           (@py_format7)
   2888: LOAD_GLOBAL          (AssertionError)
   2900: LOAD_GLOBAL          (@pytest_ar)
   2912: LOAD_ATTR            (_format_explanation)
   2922: LOAD_FAST            (@py_format7)
   2924: PRECALL              (1)
   2928: CALL                 (1)
   2938: PRECALL              (1)
   2942: CALL                 (1)
   2952: RAISE_VARARGS        (1)
   2954: LOAD_CONST           (None)
   2956: COPY                 (1)
   2958: STORE_FAST           (@py_assert0)
   2960: COPY                 (1)
   2962: STORE_FAST           (@py_assert2)
   2964: STORE_FAST           (@py_assert3)
L36: 2966: LOAD_CONST           (functional_requirements)
   2968: STORE_FAST           (@py_assert0)
   2970: LOAD_FAST            (prd)
   2972: LOAD_CONST           (prd)
   2974: BINARY_SUBSCR       
   2984: STORE_FAST           (@py_assert3)
   2986: LOAD_FAST            (@py_assert0)
   2988: LOAD_FAST            (@py_assert3)
   2990: CONTAINS_OP          (0)
   2992: STORE_FAST           (@py_assert2)
   2994: LOAD_FAST            (@py_assert2)
   2996: POP_JUMP_FORWARD_IF_TRUE (3214)
   2998: LOAD_GLOBAL          (@pytest_ar)
   3010: LOAD_ATTR            (_call_reprcompare)
   3020: LOAD_CONST           (('in',))
   3022: LOAD_FAST            (@py_assert2)
   3024: BUILD_TUPLE          (1)
   3026: LOAD_CONST           (('%(py1)s in %(py4)s',))
   3028: LOAD_FAST            (@py_assert0)
   3030: LOAD_FAST            (@py_assert3)
   3032: BUILD_TUPLE          (2)
   3034: PRECALL              (4)
   3038: CALL                 (4)
   3048: LOAD_GLOBAL          (@pytest_ar)
   3060: LOAD_ATTR            (_saferepr)
   3070: LOAD_FAST            (@py_assert0)
   3072: PRECALL              (1)
   3076: CALL                 (1)
   3086: LOAD_GLOBAL          (@pytest_ar)
   3098: LOAD_ATTR            (_saferepr)
   3108: LOAD_FAST            (@py_assert3)
   3110: PRECALL              (1)
   3114: CALL                 (1)
   3124: LOAD_CONST           (('py1', 'py4'))
   3126: BUILD_CONST_KEY_MAP  (2)
   3128: BINARY_OP            (6)
   3132: STORE_FAST           (@py_format5)
   3134: LOAD_CONST           (assert %(py6)s)
   3136: LOAD_CONST           (py6)
   3138: LOAD_FAST            (@py_format5)
   3140: BUILD_MAP            (1)
   3142: BINARY_OP            (6)
   3146: STORE_FAST           (@py_format7)
   3148: LOAD_GLOBAL          (AssertionError)
   3160: LOAD_GLOBAL          (@pytest_ar)
   3172: LOAD_ATTR            (_format_explanation)
   3182: LOAD_FAST            (@py_format7)
   3184: PRECALL              (1)
   3188: CALL                 (1)
   3198: PRECALL              (1)
   3202: CALL                 (1)
   3212: RAISE_VARARGS        (1)
   3214: LOAD_CONST           (None)
   3216: COPY                 (1)
   3218: STORE_FAST           (@py_assert0)
   3220: COPY                 (1)
   3222: STORE_FAST           (@py_assert2)
   3224: STORE_FAST           (@py_assert3)
L37: 3226: LOAD_FAST            (prd)
   3228: LOAD_CONST           (prd)
   3230: BINARY_SUBSCR       
   3240: LOAD_CONST           (user_stories)
   3242: BINARY_SUBSCR       
   3252: STORE_FAST           (@py_assert1)
   3254: LOAD_GLOBAL          (len)
   3266: LOAD_FAST            (@py_assert1)
   3268: PRECALL              (1)
   3272: CALL                 (1)
   3282: STORE_FAST           (@py_assert3)
   3284: LOAD_CONST           (0)
   3286: STORE_FAST           (@py_assert6)
   3288: LOAD_FAST            (@py_assert3)
   3290: LOAD_FAST            (@py_assert6)
   3292: COMPARE_OP           (>)
   3298: STORE_FAST           (@py_assert5)
   3300: LOAD_FAST            (@py_assert5)
   3302: POP_JUMP_FORWARD_IF_TRUE (3702)
   3304: LOAD_GLOBAL          (@pytest_ar)
   3316: LOAD_ATTR            (_call_reprcompare)
   3326: LOAD_CONST           (('>',))
   3328: LOAD_FAST            (@py_assert5)
   3330: BUILD_TUPLE          (1)
   3332: LOAD_CONST           (('%(py4)s\n{%(py4)s = %(py0)s(%(py2)s)\n} > %(py7)s',))
   3334: LOAD_FAST            (@py_assert3)
   3336: LOAD_FAST            (@py_assert6)
   3338: BUILD_TUPLE          (2)
   3340: PRECALL              (4)
   3344: CALL                 (4)
   3354: LOAD_CONST           (len)
   3356: LOAD_GLOBAL          (@py_builtins)
   3368: LOAD_ATTR            (locals)
   3378: PRECALL              (0)
   3382: CALL                 (0)
   3392: CONTAINS_OP          (0)
   3394: POP_JUMP_FORWARD_IF_TRUE (3446)
   3396: LOAD_GLOBAL          (@pytest_ar)
   3408: LOAD_ATTR            (_should_repr_global_name)
   3418: LOAD_GLOBAL          (len)
   3430: PRECALL              (1)
   3434: CALL                 (1)
   3444: POP_JUMP_FORWARD_IF_FALSE (3496)
   3446: LOAD_GLOBAL          (@pytest_ar)
   3458: LOAD_ATTR            (_saferepr)
   3468: LOAD_GLOBAL          (len)
   3480: PRECALL              (1)
   3484: CALL                 (1)
   3494: JUMP_FORWARD         (3498)
   3496: LOAD_CONST           (len)
   3498: LOAD_GLOBAL          (@pytest_ar)
   3510: LOAD_ATTR            (_saferepr)
   3520: LOAD_FAST            (@py_assert1)
   3522: PRECALL              (1)
   3526: CALL                 (1)
   3536: LOAD_GLOBAL          (@pytest_ar)
   3548: LOAD_ATTR            (_saferepr)
   3558: LOAD_FAST            (@py_assert3)
   3560: PRECALL              (1)
   3564: CALL                 (1)
   3574: LOAD_GLOBAL          (@pytest_ar)
   3586: LOAD_ATTR            (_saferepr)
   3596: LOAD_FAST            (@py_assert6)
   3598: PRECALL              (1)
   3602: CALL                 (1)
   3612: LOAD_CONST           (('py0', 'py2', 'py4', 'py7'))
   3614: BUILD_CONST_KEY_MAP  (4)
   3616: BINARY_OP            (6)
   3620: STORE_FAST           (@py_format8)
   3622: LOAD_CONST           (assert %(py9)s)
   3624: LOAD_CONST           (py9)
   3626: LOAD_FAST            (@py_format8)
   3628: BUILD_MAP            (1)
   3630: BINARY_OP            (6)
   3634: STORE_FAST           (@py_format10)
   3636: LOAD_GLOBAL          (AssertionError)
   3648: LOAD_GLOBAL          (@pytest_ar)
   3660: LOAD_ATTR            (_format_explanation)
   3670: LOAD_FAST            (@py_format10)
   3672: PRECALL              (1)
   3676: CALL                 (1)
   3686: PRECALL              (1)
   3690: CALL                 (1)
   3700: RAISE_VARARGS        (1)
   3702: LOAD_CONST           (None)
   3704: COPY                 (1)
   3706: STORE_FAST           (@py_assert1)
   3708: COPY                 (1)
   3710: STORE_FAST           (@py_assert3)
   3712: COPY                 (1)
   3714: STORE_FAST           (@py_assert5)
   3716: STORE_FAST           (@py_assert6)
L38: 3718: LOAD_GLOBAL          (print)
   3730: LOAD_CONST           (S3 PASS: PRD generated with )
   3732: LOAD_GLOBAL          (len)
   3744: LOAD_FAST            (prd)
   3746: LOAD_CONST           (prd)
   3748: BINARY_SUBSCR       
   3758: LOAD_CONST           (functional_requirements)
   3760: BINARY_SUBSCR       
   3770: PRECALL              (1)
   3774: CALL                 (1)
   3784: FORMAT_VALUE         ((None, False))
   3786: LOAD_CONST           ( FRs)
   3788: BUILD_STRING         (3)
   3790: PRECALL              (1)
   3794: CALL                 (1)
   3804: POP_TOP             
L41: 3806: LOAD_GLOBAL          (S4ArchitectureAgent)
   3818: PRECALL              (0)
   3822: CALL                 (0)
   3832: STORE_FAST           (s4)
L42: 3834: LOAD_FAST            (s4)
   3836: LOAD_METHOD          (run)
   3858: LOAD_CONST           (prd)
   3860: LOAD_FAST            (prd)
   3862: LOAD_CONST           (prd)
   3864: BINARY_SUBSCR       
   3874: BUILD_MAP            (1)
   3876: PRECALL              (1)
   3880: CALL                 (1)
   3890: STORE_FAST           (arch)
L43: 3892: LOAD_FAST            (arch)
   3894: LOAD_CONST           (status)
   3896: BINARY_SUBSCR       
   3906: STORE_FAST           (@py_assert0)
   3908: LOAD_CONST           (complete)
   3910: STORE_FAST           (@py_assert3)
   3912: LOAD_FAST            (@py_assert0)
   3914: LOAD_FAST            (@py_assert3)
   3916: COMPARE_OP           (==)
   3922: STORE_FAST           (@py_assert2)
   3924: LOAD_FAST            (@py_assert2)
   3926: POP_JUMP_FORWARD_IF_TRUE (4144)
   3928: LOAD_GLOBAL          (@pytest_ar)
   3940: LOAD_ATTR            (_call_reprcompare)
   3950: LOAD_CONST           (('==',))
   3952: LOAD_FAST            (@py_assert2)
   3954: BUILD_TUPLE          (1)
   3956: LOAD_CONST           (('%(py1)s == %(py4)s',))
   3958: LOAD_FAST            (@py_assert0)
   3960: LOAD_FAST            (@py_assert3)
   3962: BUILD_TUPLE          (2)
   3964: PRECALL              (4)
   3968: CALL                 (4)
   3978: LOAD_GLOBAL          (@pytest_ar)
   3990: LOAD_ATTR            (_saferepr)
   4000: LOAD_FAST            (@py_assert0)
   4002: PRECALL              (1)
   4006: CALL                 (1)
   4016: LOAD_GLOBAL          (@pytest_ar)
   4028: LOAD_ATTR            (_saferepr)
   4038: LOAD_FAST            (@py_assert3)
   4040: PRECALL              (1)
   4044: CALL                 (1)
   4054: LOAD_CONST           (('py1', 'py4'))
   4056: BUILD_CONST_KEY_MAP  (2)
   4058: BINARY_OP            (6)
   4062: STORE_FAST           (@py_format5)
   4064: LOAD_CONST           (assert %(py6)s)
   4066: LOAD_CONST           (py6)
   4068: LOAD_FAST            (@py_format5)
   4070: BUILD_MAP            (1)
   4072: BINARY_OP            (6)
   4076: STORE_FAST           (@py_format7)
   4078: LOAD_GLOBAL          (AssertionError)
   4090: LOAD_GLOBAL          (@pytest_ar)
   4102: LOAD_ATTR            (_format_explanation)
   4112: LOAD_FAST            (@py_format7)
   4114: PRECALL              (1)
   4118: CALL                 (1)
   4128: PRECALL              (1)
   4132: CALL                 (1)
   4142: RAISE_VARARGS        (1)
   4144: LOAD_CONST           (None)
   4146: COPY                 (1)
   4148: STORE_FAST           (@py_assert0)
   4150: COPY                 (1)
   4152: STORE_FAST           (@py_assert2)
   4154: STORE_FAST           (@py_assert3)
L44: 4156: LOAD_FAST            (arch)
   4158: LOAD_CONST           (architecture)
   4160: BINARY_SUBSCR       
   4170: LOAD_CONST           (components)
   4172: BINARY_SUBSCR       
   4182: STORE_FAST           (@py_assert1)
   4184: LOAD_GLOBAL          (len)
   4196: LOAD_FAST            (@py_assert1)
   4198: PRECALL              (1)
   4202: CALL                 (1)
   4212: STORE_FAST           (@py_assert3)
   4214: LOAD_CONST           (4)
   4216: STORE_FAST           (@py_assert6)
   4218: LOAD_FAST            (@py_assert3)
   4220: LOAD_FAST            (@py_assert6)
   4222: COMPARE_OP           (>=)
   4228: STORE_FAST           (@py_assert5)
   4230: LOAD_FAST            (@py_assert5)
   4232: POP_JUMP_FORWARD_IF_TRUE (4632)
   4234: LOAD_GLOBAL          (@pytest_ar)
   4246: LOAD_ATTR            (_call_reprcompare)
   4256: LOAD_CONST           (('>=',))
   4258: LOAD_FAST            (@py_assert5)
   4260: BUILD_TUPLE          (1)
   4262: LOAD_CONST           (('%(py4)s\n{%(py4)s = %(py0)s(%(py2)s)\n} >= %(py7)s',))
   4264: LOAD_FAST            (@py_assert3)
   4266: LOAD_FAST            (@py_assert6)
   4268: BUILD_TUPLE          (2)
   4270: PRECALL              (4)
   4274: CALL                 (4)
   4284: LOAD_CONST           (len)
   4286: LOAD_GLOBAL          (@py_builtins)
   4298: LOAD_ATTR            (locals)
   4308: PRECALL              (0)
   4312: CALL                 (0)
   4322: CONTAINS_OP          (0)
   4324: POP_JUMP_FORWARD_IF_TRUE (4376)
   4326: LOAD_GLOBAL          (@pytest_ar)
   4338: LOAD_ATTR            (_should_repr_global_name)
   4348: LOAD_GLOBAL          (len)
   4360: PRECALL              (1)
   4364: CALL                 (1)
   4374: POP_JUMP_FORWARD_IF_FALSE (4426)
   4376: LOAD_GLOBAL          (@pytest_ar)
   4388: LOAD_ATTR            (_saferepr)
   4398: LOAD_GLOBAL          (len)
   4410: PRECALL              (1)
   4414: CALL                 (1)
   4424: JUMP_FORWARD         (4428)
   4426: LOAD_CONST           (len)
   4428: LOAD_GLOBAL          (@pytest_ar)
   4440: LOAD_ATTR            (_saferepr)
   4450: LOAD_FAST            (@py_assert1)
   4452: PRECALL              (1)
   4456: CALL                 (1)
   4466: LOAD_GLOBAL          (@pytest_ar)
   4478: LOAD_ATTR            (_saferepr)
   4488: LOAD_FAST            (@py_assert3)
   4490: PRECALL              (1)
   4494: CALL                 (1)
   4504: LOAD_GLOBAL          (@pytest_ar)
   4516: LOAD_ATTR            (_saferepr)
   4526: LOAD_FAST            (@py_assert6)
   4528: PRECALL              (1)
   4532: CALL                 (1)
   4542: LOAD_CONST           (('py0', 'py2', 'py4', 'py7'))
   4544: BUILD_CONST_KEY_MAP  (4)
   4546: BINARY_OP            (6)
   4550: STORE_FAST           (@py_format8)
   4552: LOAD_CONST           (assert %(py9)s)
   4554: LOAD_CONST           (py9)
   4556: LOAD_FAST            (@py_format8)
   4558: BUILD_MAP            (1)
   4560: BINARY_OP            (6)
   4564: STORE_FAST           (@py_format10)
   4566: LOAD_GLOBAL          (AssertionError)
   4578: LOAD_GLOBAL          (@pytest_ar)
   4590: LOAD_ATTR            (_format_explanation)
   4600: LOAD_FAST            (@py_format10)
   4602: PRECALL              (1)
   4606: CALL                 (1)
   4616: PRECALL              (1)
   4620: CALL                 (1)
   4630: RAISE_VARARGS        (1)
   4632: LOAD_CONST           (None)
   4634: COPY                 (1)
   4636: STORE_FAST           (@py_assert1)
   4638: COPY                 (1)
   4640: STORE_FAST           (@py_assert3)
   4642: COPY                 (1)
   4644: STORE_FAST           (@py_assert5)
   4646: STORE_FAST           (@py_assert6)
L45: 4648: LOAD_FAST            (arch)
   4650: LOAD_CONST           (architecture)
   4652: BINARY_SUBSCR       
   4662: LOAD_CONST           (data_flow)
   4664: BINARY_SUBSCR       
   4674: STORE_FAST           (@py_assert1)
   4676: LOAD_GLOBAL          (len)
   4688: LOAD_FAST            (@py_assert1)
   4690: PRECALL              (1)
   4694: CALL                 (1)
   4704: STORE_FAST           (@py_assert3)
   4706: LOAD_CONST           (0)
   4708: STORE_FAST           (@py_assert6)
   4710: LOAD_FAST            (@py_assert3)
   4712: LOAD_FAST            (@py_assert6)
   4714: COMPARE_OP           (>)
   4720: STORE_FAST           (@py_assert5)
   4722: LOAD_FAST            (@py_assert5)
   4724: POP_JUMP_FORWARD_IF_TRUE (5124)
   4726: LOAD_GLOBAL          (@pytest_ar)
   4738: LOAD_ATTR            (_call_reprcompare)
   4748: LOAD_CONST           (('>',))
   4750: LOAD_FAST            (@py_assert5)
   4752: BUILD_TUPLE          (1)
   4754: LOAD_CONST           (('%(py4)s\n{%(py4)s = %(py0)s(%(py2)s)\n} > %(py7)s',))
   4756: LOAD_FAST            (@py_assert3)
   4758: LOAD_FAST            (@py_assert6)
   4760: BUILD_TUPLE          (2)
   4762: PRECALL              (4)
   4766: CALL                 (4)
   4776: LOAD_CONST           (len)
   4778: LOAD_GLOBAL          (@py_builtins)
   4790: LOAD_ATTR            (locals)
   4800: PRECALL              (0)
   4804: CALL                 (0)
   4814: CONTAINS_OP          (0)
   4816: POP_JUMP_FORWARD_IF_TRUE (4868)
   4818: LOAD_GLOBAL          (@pytest_ar)
   4830: LOAD_ATTR            (_should_repr_global_name)
   4840: LOAD_GLOBAL          (len)
   4852: PRECALL              (1)
   4856: CALL                 (1)
   4866: POP_JUMP_FORWARD_IF_FALSE (4918)
   4868: LOAD_GLOBAL          (@pytest_ar)
   4880: LOAD_ATTR            (_saferepr)
   4890: LOAD_GLOBAL          (len)
   4902: PRECALL              (1)
   4906: CALL                 (1)
   4916: JUMP_FORWARD         (4920)
   4918: LOAD_CONST           (len)
   4920: LOAD_GLOBAL          (@pytest_ar)
   4932: LOAD_ATTR            (_saferepr)
   4942: LOAD_FAST            (@py_assert1)
   4944: PRECALL              (1)
   4948: CALL                 (1)
   4958: LOAD_GLOBAL          (@pytest_ar)
   4970: LOAD_ATTR            (_saferepr)
   4980: LOAD_FAST            (@py_assert3)
   4982: PRECALL              (1)
   4986: CALL                 (1)
   4996: LOAD_GLOBAL          (@pytest_ar)
   5008: LOAD_ATTR            (_saferepr)
   5018: LOAD_FAST            (@py_assert6)
   5020: PRECALL              (1)
   5024: CALL                 (1)
   5034: LOAD_CONST           (('py0', 'py2', 'py4', 'py7'))
   5036: BUILD_CONST_KEY_MAP  (4)
   5038: BINARY_OP            (6)
   5042: STORE_FAST           (@py_format8)
   5044: LOAD_CONST           (assert %(py9)s)
   5046: LOAD_CONST           (py9)
   5048: LOAD_FAST            (@py_format8)
   5050: BUILD_MAP            (1)
   5052: BINARY_OP            (6)
   5056: STORE_FAST           (@py_format10)
   5058: LOAD_GLOBAL          (AssertionError)
   5070: LOAD_GLOBAL          (@pytest_ar)
   5082: LOAD_ATTR            (_format_explanation)
   5092: LOAD_FAST            (@py_format10)
   5094: PRECALL              (1)
   5098: CALL                 (1)
   5108: PRECALL              (1)
   5112: CALL                 (1)
   5122: RAISE_VARARGS        (1)
   5124: LOAD_CONST           (None)
   5126: COPY                 (1)
   5128: STORE_FAST           (@py_assert1)
   5130: COPY                 (1)
   5132: STORE_FAST           (@py_assert3)
   5134: COPY                 (1)
   5136: STORE_FAST           (@py_assert5)
   5138: STORE_FAST           (@py_assert6)
L46: 5140: LOAD_GLOBAL          (print)
   5152: LOAD_CONST           (S4 PASS: )
   5154: LOAD_GLOBAL          (len)
   5166: LOAD_FAST            (arch)
   5168: LOAD_CONST           (architecture)
   5170: BINARY_SUBSCR       
   5180: LOAD_CONST           (components)
   5182: BINARY_SUBSCR       
   5192: PRECALL              (1)
   5196: CALL                 (1)
   5206: FORMAT_VALUE         ((None, False))
   5208: LOAD_CONST           ( components designed)
   5210: BUILD_STRING         (3)
   5212: PRECALL              (1)
   5216: CALL                 (1)
   5226: POP_TOP             
L48: 5228: LOAD_GLOBAL          (print)
   5240: LOAD_CONST           (
S1-S4 Pipeline: ALL PASS)
   5242: PRECALL              (1)
   5246: CALL                 (1)
   5256: POP_TOP             
   5258: LOAD_CONST           (None)
   5260: RETURN_VALUE        
